noventis/__init__.py
noventis/asset/Logo.png
noventis/data_cleaner/__init__.py
noventis/data_cleaner/auto.py
noventis/data_cleaner/data_quality.py
noventis/data_cleaner/encoding.py
noventis/data_cleaner/imputing.py
noventis/data_cleaner/outlier_handling.py
noventis/data_cleaner/scaling.py
noventis/eda_auto/__init__.py
noventis/eda_auto/eda_auto.py
noventis/predictor/__init__.py
noventis/predictor/auto.py
noventis/predictor/manual.py
noventis-0.1.4.dist-info/licenses/LICENSE
noventis-0.1.4.dist-info/METADATA
noventis-0.1.4.dist-info/WHEEL
noventis-0.1.4.dist-info/top_level.txt
noventis-0.1.4.dist-info/RECORD
